bert_serving/__init__.py
bert_serving/run/__init__.py
bert_serving/server/conf/cube.conf
bert_serving/server/conf/gflags.conf
bert_serving/server/conf/model_toolkit.prototxt
bert_serving/server/conf/model_toolkit.prototxt.bk
bert_serving/server/conf/resource.prototxt
bert_serving/server/conf/service.prototxt
bert_serving/server/conf/workflow.prototxt
bert_serving/server/data/model/paddle/fluid_reload_flag
bert_serving/server/data/model/paddle/fluid_time_file
bert_serving-0.0.1.dist-info/LICENSE
bert_serving-0.0.1.dist-info/METADATA
bert_serving-0.0.1.dist-info/WHEEL
bert_serving-0.0.1.dist-info/top_level.txt
bert_serving-0.0.1.dist-info/RECORD
